[{"label": null, "term": "Feeder UCITS", "predicted_labels": ["Funds", "Future", "Stocks", "Option", "Swap"]}, {"label": null, "term": "Cash settled future", "predicted_labels": ["Future", "MMIs", "Forward", "Option", "Funds"]}, {"label": null, "term": "Green bond", "predicted_labels": ["Bonds", "Stocks", "Funds", "Future", "MMIs"]}, {"label": null, "term": "Index Forward", "predicted_labels": ["Forward", "Option", "Future", "Funds", "Swap"]}, {"label": null, "term": "Over-the-counter option", "predicted_labels": ["Option", "MMIs", "Future", "Swap", "Funds"]}, {"label": null, "term": "Restricted securities", "predicted_labels": ["MMIs", "Stocks", "Bonds", "Funds", "Future"]}, {"label": null, "term": "Class A shares", "predicted_labels": ["Stocks", "Funds", "MMIs", "Bonds", "Forward"]}, {"label": null, "term": "Bankers acceptances", "predicted_labels": ["Funds", "Future", "Bonds", "MMIs", "Swap"]}, {"label": null, "term": "Preference share", "predicted_labels": ["Stocks", "Funds", "Bonds", "MMIs", "Swap"]}, {"label": null, "term": "Alternative investment fund", "predicted_labels": ["Funds", "Bonds", "Stocks", "Future", "MMIs"]}, {"label": null, "term": "NDF", "predicted_labels": ["Bonds", "Swap", "Stocks", "Funds", "MMIs"]}, {"label": null, "term": "Commodity index swap", "predicted_labels": ["Future", "Swap", "Option", "Forward", "MMIs"]}, {"label": null, "term": "Cash-settled option", "predicted_labels": ["Option", "MMIs", "Funds", "Swap", "Bonds"]}, {"label": null, "term": "IRS", "predicted_labels": ["MMIs", "Funds", "Stocks", "Forward", "Option"]}, {"label": null, "term": "TIPS", "predicted_labels": ["Bonds", "Stocks", "Option", "Swap", "MMIs"]}, {"label": null, "term": "Bond coupon", "predicted_labels": ["Bonds", "Option", "Future", "Stocks", "Swap"]}, {"label": null, "term": "Perpetual bond", "predicted_labels": ["Bonds", "Funds", "Stocks", "Future", "MMIs"]}, {"label": null, "term": "Stock index futures", "predicted_labels": ["Stocks", "Forward", "Future", "Option", "MMIs"]}, {"label": null, "term": "Municipal bonds", "predicted_labels": ["Bonds", "MMIs", "Funds", "Forward", "Stocks"]}, {"label": null, "term": "Class B shares", "predicted_labels": ["Stocks", "Funds", "Forward", "MMIs", "Bonds"]}, {"label": null, "term": "Eurobond", "predicted_labels": ["Bonds", "Option", "Future", "Stocks", "Funds"]}, {"label": null, "term": "Commodity future", "predicted_labels": ["Future", "Forward", "Stocks", "Option", "Funds"]}, {"label": null, "term": "Foreign exchange swap", "predicted_labels": ["Forward", "Swap", "Funds", "Option", "Bonds"]}, {"label": null, "term": "High-risk bonds", "predicted_labels": ["Bonds", "Funds", "Stocks", "MMIs", "Option"]}, {"label": null, "term": "Cleared swap", "predicted_labels": ["Swap", "Forward", "Funds", "MMIs", "Option"]}, {"label": null, "term": "US stock", "predicted_labels": ["Stocks", "Bonds", "MMIs", "Forward", "Funds"]}, {"label": null, "term": "Forward swap", "predicted_labels": ["Forward", "Swap", "Future", "Option", "Funds"]}, {"label": null, "term": "Buyback option", "predicted_labels": ["Option", "Forward", "Funds", "MMIs", "Swap"]}, {"label": null, "term": "T-note", "predicted_labels": ["Stocks", "MMIs", "Bonds", "Funds", "Forward"]}, {"label": null, "term": "Listed bond", "predicted_labels": ["Stocks", "Bonds", "Funds", "Option", "MMIs"]}, {"label": null, "term": "Pay-in-kind bonds", "predicted_labels": ["MMIs", "Bonds", "Stocks", "Funds", "Option"]}, {"label": null, "term": "Mortgage bond", "predicted_labels": ["Bonds", "Future", "Stocks", "MMIs", "Funds"]}, {"label": null, "term": "Equity basket swap", "predicted_labels": ["Swap", "Future", "Option", "Forward", "Funds"]}, {"label": null, "term": "Equity swap", "predicted_labels": ["Future", "Swap", "Option", "Forward", "Funds"]}, {"label": null, "term": "High grade bond", "predicted_labels": ["Bonds", "Funds", "Forward", "Stocks", "MMIs"]}, {"label": null, "term": "Long term bond", "predicted_labels": ["Bonds", "Future", "Funds", "MMIs", "Stocks"]}, {"label": null, "term": "Inflation indexed bond", "predicted_labels": ["Bonds", "MMIs", "Future", "Stocks", "Forward"]}, {"label": null, "term": "International depository receipt", "predicted_labels": ["Stocks", "MMIs", "Bonds", "Future", "Forward"]}, {"label": null, "term": "Corporate bond", "predicted_labels": ["Bonds", "Stocks", "Future", "Funds", "MMIs"]}, {"label": null, "term": "Hedge fund", "predicted_labels": ["Funds", "Forward", "Stocks", "Bonds", "MMIs"]}, {"label": null, "term": "Dividend future", "predicted_labels": ["Future", "Forward", "Stocks", "Funds", "Option"]}, {"label": null, "term": "Low-risk bonds", "predicted_labels": ["Bonds", "Funds", "Option", "MMIs", "Swap"]}, {"label": null, "term": "Outright Forward", "predicted_labels": ["Forward", "Stocks", "Future", "Funds", "Option"]}, {"label": null, "term": "Callable bond", "predicted_labels": ["Bonds", "Stocks", "Funds", "Future", "MMIs"]}, {"label": null, "term": "UCITS fund", "predicted_labels": ["Funds", "Stocks", "Bonds", "MMIs", "Forward"]}, {"label": null, "term": "Credit enhancement", "predicted_labels": ["Swap", "Bonds", "Stocks", "MMIs", "Funds"]}, {"label": null, "term": "Reverse convertible bond", "predicted_labels": ["Bonds", "Stocks", "Future", "MMIs", "Funds"]}, {"label": null, "term": "FX future", "predicted_labels": ["Forward", "Future", "Stocks", "MMIs", "Option"]}, {"label": null, "term": "ABS", "predicted_labels": ["Bonds", "Funds", "Swap", "MMIs", "Option"]}, {"label": null, "term": "Index fund", "predicted_labels": ["Funds", "Option", "Stocks", "Future", "Bonds"]}, {"label": null, "term": "Stock future", "predicted_labels": ["Stocks", "Future", "Forward", "Option", "Funds"]}, {"label": null, "term": "Government bond", "predicted_labels": ["Bonds", "MMIs", "Stocks", "Future", "Funds"]}, {"label": null, "term": "Large-cap stock", "predicted_labels": ["Stocks", "Funds", "MMIs", "Bonds", "Option"]}, {"label": null, "term": "Listed option", "predicted_labels": ["Option", "Stocks", "Funds", "Bonds", "MMIs"]}, {"label": null, "term": "Options on equities", "predicted_labels": ["Option", "Stocks", "Funds", "MMIs", "Forward"]}, {"label": null, "term": "Federal bond", "predicted_labels": ["Bonds", "Option", "Future", "Stocks", "MMIs"]}, {"label": null, "term": "Zero coupon bond", "predicted_labels": ["Bonds", "Stocks", "Option", "Swap", "Future"]}, {"label": null, "term": "Put option", "predicted_labels": ["Option", "MMIs", "Swap", "Forward", "Future"]}, {"label": null, "term": "Interest rate swap", "predicted_labels": ["Swap", "Forward", "Future", "Bonds", "Option"]}, {"label": null, "term": "Subordinated bond", "predicted_labels": ["Bonds", "Stocks", "Forward", "Future", "Funds"]}, {"label": null, "term": "OTC options", "predicted_labels": ["Swap", "Option", "Future", "Forward", "Stocks"]}, {"label": null, "term": "Call option", "predicted_labels": ["Option", "MMIs", "Funds", "Bonds", "Swap"]}, {"label": null, "term": "Options on commodities", "predicted_labels": ["Option", "MMIs", "Future", "Stocks", "Forward"]}, {"label": null, "term": "CDS", "predicted_labels": ["Swap", "Forward", "MMIs", "Bonds", "Future"]}, {"label": null, "term": "Yankee bonds", "predicted_labels": ["Bonds", "MMIs", "Funds", "Stocks", "Option"]}, {"label": null, "term": "Futures on securities", "predicted_labels": ["Option", "Future", "Forward", "Stocks", "MMIs"]}, {"label": null, "term": "Bond fund", "predicted_labels": ["Bonds", "Funds", "Future", "Option", "MMIs"]}, {"label": null, "term": "Unit trust", "predicted_labels": ["Stocks", "Funds", "MMIs", "Forward", "Future"]}, {"label": null, "term": "E-mini", "predicted_labels": ["Stocks", "MMIs", "Funds", "Forward", "Swap"]}, {"label": null, "term": "Convertible bond", "predicted_labels": ["Bonds", "Stocks", "Future", "MMIs", "Funds"]}, {"label": null, "term": "Equity default swap", "predicted_labels": ["Swap", "Future", "Option", "Forward", "Bonds"]}, {"label": null, "term": "Uncleared swap", "predicted_labels": ["Swap", "Forward", "Funds", "MMIs", "Option"]}, {"label": null, "term": "Inflation index swap", "predicted_labels": ["Swap", "Forward", "Option", "MMIs", "Future"]}, {"label": null, "term": "Bills of exchange", "predicted_labels": ["MMIs", "Forward", "Funds", "Option", "Bonds"]}, {"label": null, "term": "Warrant-linked bond", "predicted_labels": ["Bonds", "MMIs", "Swap", "Stocks", "Option"]}, {"label": null, "term": "Credit linked notes", "predicted_labels": ["Bonds", "Swap", "MMIs", "Stocks", "Forward"]}, {"label": null, "term": "FX swap", "predicted_labels": ["Forward", "Swap", "MMIs", "Option", "Future"]}, {"label": null, "term": "Equity option", "predicted_labels": ["Option", "Future", "Bonds", "Funds", "MMIs"]}, {"label": null, "term": "Floating rate note", "predicted_labels": ["Bonds", "Stocks", "MMIs", "Future", "Forward"]}, {"label": null, "term": "T-bill", "predicted_labels": ["MMIs", "Stocks", "Funds", "Swap", "Bonds"]}, {"label": null, "term": "Exchange traded options", "predicted_labels": ["Option", "Funds", "Forward", "MMIs", "Stocks"]}, {"label": null, "term": "Fixed income future", "predicted_labels": ["Future", "Bonds", "Forward", "Stocks", "MMIs"]}, {"label": null, "term": "Offsetting swap", "predicted_labels": ["Swap", "Forward", "MMIs", "Option", "Funds"]}, {"label": null, "term": "SICAV", "predicted_labels": ["Funds", "Stocks", "Swap", "Bonds", "MMIs"]}, {"label": null, "term": "Collective investment scheme", "predicted_labels": ["Funds", "Stocks", "Bonds", "MMIs", "Swap"]}, {"label": null, "term": "Unfunded TRS", "predicted_labels": ["Swap", "Funds", "Stocks", "Bonds", "Forward"]}, {"label": null, "term": "Treasury securities", "predicted_labels": ["MMIs", "Bonds", "Funds", "Stocks", "Forward"]}, {"label": null, "term": "Foreign Exchange Forward", "predicted_labels": ["Forward", "Future", "Funds", "Option", "Bonds"]}, {"label": null, "term": "Asset-backed securities", "predicted_labels": ["Bonds", "Funds", "Stocks", "MMIs", "Forward"]}, {"label": null, "term": "Repurchase option", "predicted_labels": ["Option", "Bonds", "Swap", "MMIs", "Future"]}, {"label": null, "term": "Depositary receipt", "predicted_labels": ["Stocks", "MMIs", "Funds", "Forward", "Option"]}, {"label": null, "term": "Junk bonds", "predicted_labels": ["Bonds", "Funds", "MMIs", "Stocks", "Future"]}, {"label": null, "term": "Pooled fund", "predicted_labels": ["Funds", "Bonds", "Stocks", "MMIs", "Forward"]}, {"label": null, "term": "Fixed-income funds", "predicted_labels": ["Funds", "Bonds", "Stocks", "MMIs", "Swap"]}, {"label": null, "term": "Currency swap", "predicted_labels": ["Forward", "Swap", "Option", "Future", "MMIs"]}, {"label": null, "term": "EDS", "predicted_labels": ["Swap", "MMIs", "Forward", "Bonds", "Funds"]}, {"label": null, "term": "Promissory note", "predicted_labels": ["Bonds", "Stocks", "MMIs", "Future", "Forward"]}, {"label": null, "term": "Bearer bond", "predicted_labels": ["MMIs", "Bonds", "Funds", "Stocks", "Future"]}, {"label": null, "term": "Zero coupon swap", "predicted_labels": ["Swap", "Forward", "Option", "Bonds", "MMIs"]}]